columns/__init__.py
columns/__main__.py
columns/columns.py
columns-0.0.2.dist-info/METADATA
columns-0.0.2.dist-info/RECORD
columns-0.0.2.dist-info/WHEEL
columns-0.0.2.dist-info/entry_points.txt
columns-0.0.2.dist-info/top_level.txt
